<?xml version="1.0"?>

<!-- Nosewheel steering, handle and/or pedals -->

<PropertyList>

<model>
 <path>sw_steering-mode.xml</path>
  <offsets>
    <pitch-deg>-25</pitch-deg>
    <x-m>2.118</x-m>
    <y-m>-0.86256</y-m>
    <z-m>0.662</z-m>
  </offsets>
</model>

<model>
 <path>wl_handle_on.xml</path>
  <offsets>
    <x-m>2.09972</x-m>
    <y-m>-0.87</y-m>
    <z-m>0.71</z-m>
  </offsets>
</model>

<model>
 <path>wl_pedals_armed.xml</path>
  <offsets>
    <x-m>2.09972</x-m>
    <y-m>-0.84</y-m>
    <z-m>0.71</z-m>
  </offsets>
</model>

<model>
 <path>wl_pedals_on.xml</path>
  <offsets>
    <x-m>2.09972</x-m>
    <y-m>-0.81</y-m>
    <z-m>0.71</z-m>
  </offsets>
</model>

<!-- Brakes - Anti-Skid -->

<model>
 <path>sw_anti-skid.xml</path>
  <offsets>
    <pitch-deg>-25</pitch-deg>
    <x-m>2.117</x-m>
    <y-m>-0.2744</y-m>
    <z-m>0.6859</z-m>
  </offsets>
</model>

<model>
 <path>wl_anti-skid_left.xml</path>
  <offsets>
  <pitch-deg>-25</pitch-deg>
    <x-m>2.112</x-m>
    <y-m>-0.3024</y-m>
    <z-m>0.6972</z-m>
  </offsets>
</model>

<model>
 <path>wl_anti-skid_right.xml</path>
  <offsets>
  <pitch-deg>-25</pitch-deg>
    <x-m>2.112</x-m>
    <y-m>-0.2449</y-m>
    <z-m>0.6972</z-m>
  </offsets>
</model>

<!-- Gear unknown on left console -->

<model>
 <path>unknown_sw_gear_lc01.xml</path>
  <offsets>
    <x-m>2.5574</x-m>
    <y-m>-0.9702</y-m>
    <z-m>0.5225</z-m>
    <heading-deg>84</heading-deg>
  </offsets>
</model>

<model>
 <path>unknown_sw_gear_lc02.xml</path>
  <offsets>
    <x-m>2.5182</x-m>
    <y-m>-0.9661</y-m>
    <z-m>0.5225</z-m>
    <heading-deg>84</heading-deg>
  </offsets>
</model>

<model>
 <path>unknown_wl_gear_lc01.xml</path>
  <offsets>
    <x-m>2.5574</x-m>
    <y-m>-0.9702</y-m>
    <z-m>0.58</z-m>
    <heading-deg>84</heading-deg>
  </offsets>
</model>

<model>
 <path>unknown_wl_gear_lc02.xml</path>
  <offsets>
    <x-m>2.5182</x-m>
    <y-m>-0.9661</y-m>
    <z-m>0.56</z-m>
    <heading-deg>84</heading-deg>
  </offsets>
</model>



</PropertyList>
